traumascanner/__init__.py
traumascanner/add_targets.py
traumascanner/apply_targets.py
traumascanner/export_data.py
traumascanner/import_data.py
traumascanner/text_targets.py
traumascanner/traumascanner.py
traumascanner-0.1.1.dist-info/LICENSE
traumascanner-0.1.1.dist-info/METADATA
traumascanner-0.1.1.dist-info/WHEEL
traumascanner-0.1.1.dist-info/RECORD
