Metadata-Version: 2.1
Name: traumascanner
Version: 0.1.1
Summary: Identify radiology reports with post-traumatic hemorrhage
Home-page: https://github.com/meghutch/traumaScanner/
License: MIT
Author: Meghan R. Hutch
Requires-Python: >=3.7,<4.0
Classifier: License :: OSI Approved :: MIT License
Classifier: Programming Language :: Python :: 3
Classifier: Programming Language :: Python :: 3.7
Classifier: Programming Language :: Python :: 3.8
Classifier: Programming Language :: Python :: 3.9
Classifier: Programming Language :: Python :: 3.10
Classifier: Programming Language :: Python :: 3.11
Classifier: Programming Language :: Python :: 3.12
Requires-Dist: numpy (>=1.21.6,<2.0.0)
Requires-Dist: pandas (>=1.2.5,<2.0.0)
